README.md
setup.py
loggez/__init__.py
loggez/loggez.py
loggez.egg-info/PKG-INFO
loggez.egg-info/SOURCES.txt
loggez.egg-info/dependency_links.txt
loggez.egg-info/requires.txt
loggez.egg-info/top_level.txt