Metadata-Version: 2.1
Name: loggez
Version: 0.7.6
Summary: Python Easy Logging (LOGG EZ)
Home-page: https://gitlab.com/meehai/loggez
License: WTFPL
Requires-Python: >=3.8
Requires-Dist: colorama>=0.4.6
